{
  "Friends": {
    "scan_list": [
      "All"
    ],
    "section": [
      "/friends_all"
    ],
    "elements_path": [
      "//a[@class='cu' and @xpath=',1' and text()='Friends']"
    ],
    "file_names": [
      "All_Friends.txt"
    ],
    "save_status": 0
  },
  "Photos": {
    "scan_list": [
      "Photos of"
    ],
    "section": [
      "/photos_all"
    ],
    "elements_path": [
      "//a[@class='cu' and text()='Photos']"
    ],
    "file_names": [
      "All_Photos.txt"
    ],
    "save_status": 1
  },
  "Videos": {
    "scan_list": [
      "'s Videos",
      "Videos of"
    ],
    "section": [
      "/videos_by",
      "/videos_of"
    ],
    "elements_path": [
      "//*[contains(@id, 'pagelet_timeline_app_collection_')]/ul",
      "//*[contains(@id, 'pagelet_timeline_app_collection_')]/ul"
    ],
    "file_names": [
      "Uploaded Videos.txt",
      "Tagged Videos.txt"
    ],
    "save_status": 2
  },
  "About": {
    "scan_list": [],
    "section": [
      "/about?section=overview",
      "/about?section=education",
      "/about?section=living",
      "/about?section=contact-info",
      "/about?section=relationship",
      "/about?section=bio",
      "/about?section=year-overviews"
    ],
    "elements_path": [
      "//*[contains(@id, 'pagelet_timeline_app_collection_')]/ul/li/div/div[2]/div/div",
      "//*[contains(@id, 'pagelet_timeline_app_collection_')]/ul/li/div/div[2]/div/div",
      "//*[contains(@id, 'pagelet_timeline_app_collection_')]/ul/li/div/div[2]/div/div",
      "//*[contains(@id, 'pagelet_timeline_app_collection_')]/ul/li/div/div[2]/div/div",
      "//*[contains(@id, 'pagelet_timeline_app_collection_')]/ul/li/div/div[2]/div/div",
      "//*[contains(@id, 'pagelet_timeline_app_collection_')]/ul/li/div/div[2]/div/div",
      "//*[contains(@id, 'pagelet_timeline_app_collection_')]/ul/li/div/div[2]/div/div"
    ],
    "file_names": [
      "Overview.txt",
      "Work and Education.txt",
      "Places Lived.txt",
      "Contact and Basic Info.txt",
      "Family and Relationships.txt",
      "Details About.txt",
      "Life Events.txt"
    ],
    "save_status": 3
  },
  "Posts": {
    "scan_list": [],
    "section": [],
    "elements_path": [
      "//div[@class='_5pcb _4b0l _2q8l']"
    ],
    "file_names": [
      "Posts.txt"
    ],
    "save_status": 4
  }
}
